{
  "ongoing": [
    {
      "title": "Kakkou no Iinazuke Season 2",
      "url": "https://meownime.ltd/kakkou-iinazuke-s2-sub-indo/#08"
    },
    {
      "title": "Kanojo, Okarishimasu Season 4",
      "url": "https://meownime.ltd/kanojo-okarishimasu-s4-sub-indo/#09"
    },
    {
      "title": "Sakamoto Days Part 2",
      "url": "https://meownime.ltd/sakamoto-days-part-2-sub-indo/#08"
    },
    {
      "title": "Grand Blue Season 2",
      "url": "https://meownime.ltd/grand-blue-season-2-episode-01-subtitle-indonesia/#08"
    },
    {
      "title": "Aldnoah.Zero Season 2",
      "url": "https://meownime.ltd/aldzero-s2-sub-indo/"
    }
  ],
  "completed": [
    {
      "title": "Necronomico no Cosmic Horror Show",
      "url": "https://meownime.ltd/necronomico-horror-show-sub-indo/#09"
    },
    {
      "title": "Watanare",
      "url": "https://meownime.ltd/watanare-sub-indo/#08"
    },
    {
      "title": "Aldnoah.Zero",
      "url": "https://meownime.ltd/aldzero-sub-indo/"
    },
    {
      "title": "Val x Love",
      "url": "https://meownime.ltd/val-love-sub-indo/"
    },
    {
      "title": "Uchi Tama?! Uchi no Tama Shirimasen ka?",
      "url": "https://meownime.ltd/uchitama-sub-indo/"
    },
    {
      "title": "Majutsushi Orphen Hagure Tabi",
      "url": "https://meownime.ltd/majutsushi-orphen-hagure-tabi-sub-indo/"
    },
    {
      "title": "Bakemono no Ko",
      "url": "https://meownime.ltd/bakemono-no-ko-sub-indo/"
    },
    {
      "title": "No Game No Life: Zero",
      "url": "https://meownime.ltd/no-game-no-life-zero-sub-indo/"
    },
    {
      "title": "Kimi no Na wa.",
      "url": "https://meownime.ltd/kimi-no-na-wa-sub-indo/"
    }
  ],
  "movies": [
    {
      "title": "Youjo Senki Movie",
      "url": "https://meownime.ltd/youjo-senki-movie-sub-indo/"
    },
    {
      "title": "Sword Art Online Movie: Ordinal Scale",
      "url": "https://meownime.ltd/swag-ordiscale-sub-indo/"
    }
  ]
}